[{"name":"opacity/024","resolvedType":"FLOAT","description":"24%. Light scrim.","valuesByMode":{"default":0.24}},{"name":"opacity/040","resolvedType":"FLOAT","description":"40%. Medium scrim \u2014 disabled control body.","valuesByMode":{"default":0.4}},{"name":"opacity/060","resolvedType":"FLOAT","description":"60%. Standard backdrop scrim (modals, drawers).","valuesByMode":{"default":0.6}},{"name":"opacity/080","resolvedType":"FLOAT","description":"80%. Strong dimming.","valuesByMode":{"default":0.8}},{"name":"opacity/100","resolvedType":"FLOAT","description":"100%. Fully opaque (ergonomic shortcut).","valuesByMode":{"default":1.0}},{"name":"font-size/10","resolvedType":"FLOAT","description":"12px. Caption: metadata, legal text, table headers. (px)","valuesByMode":{"default":12.0}},{"name":"font-size/20","resolvedType":"FLOAT","description":"14px. Small body: secondary copy, dense UI, inputs. (px)","valuesByMode":{"default":14.0}},{"name":"font-size/30","resolvedType":"FLOAT","description":"16px. Default body: reading size. (px)","valuesByMode":{"default":16.0}},{"name":"font-size/40","resolvedType":"FLOAT","description":"18px. Large body: emphasized paragraphs. (px)","valuesByMode":{"default":18.0}},{"name":"font-size/50","resolvedType":"FLOAT","description":"20px. Subheading: in-page section labels. (px)","valuesByMode":{"default":20.0}},{"name":"font-size/60","resolvedType":"FLOAT","description":"24px. Heading-3: within-section titles. (px)","valuesByMode":{"default":24.0}},{"name":"font-size/80","resolvedType":"FLOAT","description":"32px. Heading-2: major-section titles. (px)","valuesByMode":{"default":32.0}},{"name":"font-size/90","resolvedType":"FLOAT","description":"36px. Reserved tuning step. (px)","valuesByMode":{"default":36.0}},{"name":"font-size/100","resolvedType":"FLOAT","description":"40px. Heading-1: page titles. (px)","valuesByMode":{"default":40.0}},{"name":"font-size/120","resolvedType":"FLOAT","description":"48px. Display-small: hero subtitles. (px)","valuesByMode":{"default":48.0}},{"name":"font-size/160","resolvedType":"FLOAT","description":"64px. Display-large: hero titles. (px)","valuesByMode":{"default":64.0}},{"name":"line-height/10","resolvedType":"FLOAT","description":"Tight. Display typography, uppercase, monospace blocks.","valuesByMode":{"default":1.0}},{"name":"line-height/20","resolvedType":"FLOAT","description":"Snug. Headings, condensed UI.","valuesByMode":{"default":1.2}},{"name":"line-height/30","resolvedType":"FLOAT","description":"Default. Body text, controls.","valuesByMode":{"default":1.4}},{"name":"line-height/40","resolvedType":"FLOAT","description":"Loose. Long-form reading, prose.","valuesByMode":{"default":1.6}},{"name":"line-height/50","resolvedType":"FLOAT","description":"Airy. Captions on dense layouts.","valuesByMode":{"default":1.8}},{"name":"duration/instant","resolvedType":"FLOAT","description":"Immediate, no transition. (ms)","valuesByMode":{"default":0.0}},{"name":"duration/fast","resolvedType":"FLOAT","description":"Micro-interactions: hover, focus. (ms)","valuesByMode":{"default":100.0}},{"name":"duration/moderate","resolvedType":"FLOAT","description":"Standard UI transitions. (ms)","valuesByMode":{"default":200.0}},{"name":"duration/slow","resolvedType":"FLOAT","description":"Enter/exit: modals, drawers. (ms)","valuesByMode":{"default":400.0}}]